{
  "net.tcodes.altaufikvpn": "2.0",
  "xyz.tekidoer.austroplus.vpn": "10.0.1",
  "com.boost.vpn": "3.3",
  "com.crissenhz.servers": "31.0",
  "com.zfreevpn.dev": "Varies with device",
  "com.thomas.http": "34",
  "xyz.easypro.httpcustom": "6.9.20-RC93",
  "com.fenix.vpn": "15.2",
  "com.jirehvpn": "1.3",
  "com.fleet.vpn": "3.2.3",
  "com.vpnproxymd.mdproxyvpn": "1.0.20",
  "vpn.minapronet.com.eg": "71.0.0",
  "com.msyvpn.custom": "Varies with device",
  "com.msyvpn.lite": "Varies with device",
  "app.mtkingnet.buildd": "isvsoft 8.4.23",
  "com.peru.vpn": "Varies with device",
  "com.socketdevz.dev": "1.41",
  "rx.teamhz.plus": "37",
  "com.tunneldoom.http": "Varies with device",
  "turbo.mx.anuncios": "113.7.7",
  "com.urbanvpn.android": "1.0.97",
  "com.magmaplayer": "1.0.9",
  "com.whatsapp": "Varies with device",
  "com.pixlr.express": "3.8.2",
  "com.social.devweb.playaf": "22.0.1",
  "lyriceditor.lyricsearch.embedlyrictomp3.syncedlyriceditor": "25.7.14"
}
